aliyunsdkcdrs/__init__.py
aliyunsdkcdrs/request/__init__.py
aliyunsdkcdrs/request/v20201101/AddCdrsMonitorRequest.py
aliyunsdkcdrs/request/v20201101/BindDeviceRequest.py
aliyunsdkcdrs/request/v20201101/CreateProjectRequest.py
aliyunsdkcdrs/request/v20201101/GetCdrsMonitorListRequest.py
aliyunsdkcdrs/request/v20201101/GetCdrsMonitorResultRequest.py
aliyunsdkcdrs/request/v20201101/ListAreaHotSpotMetricsRequest.py
aliyunsdkcdrs/request/v20201101/ListCityMapAoisRequest.py
aliyunsdkcdrs/request/v20201101/ListCityMapCameraResultsRequest.py
aliyunsdkcdrs/request/v20201101/ListCityMapCameraStatisticsRequest.py
aliyunsdkcdrs/request/v20201101/ListCityMapImageDetailsRequest.py
aliyunsdkcdrs/request/v20201101/ListCityMapPersonFlowRequest.py
aliyunsdkcdrs/request/v20201101/ListCityMapRangeStatisticRequest.py
aliyunsdkcdrs/request/v20201101/ListCorpMetricsStatisticRequest.py
aliyunsdkcdrs/request/v20201101/ListDataStatisticsByDayRequest.py
aliyunsdkcdrs/request/v20201101/ListDataStatisticsRequest.py
aliyunsdkcdrs/request/v20201101/ListDeviceDetailRequest.py
aliyunsdkcdrs/request/v20201101/ListDeviceGenderStatisticsRequest.py
aliyunsdkcdrs/request/v20201101/ListDevicePersonRequest.py
aliyunsdkcdrs/request/v20201101/ListDevicePersonStatisticsRequest.py
aliyunsdkcdrs/request/v20201101/ListDeviceRelationRequest.py
aliyunsdkcdrs/request/v20201101/ListMapRouteDetailsRequest.py
aliyunsdkcdrs/request/v20201101/ListPersonDetailsRequest.py
aliyunsdkcdrs/request/v20201101/ListPersonResultRequest.py
aliyunsdkcdrs/request/v20201101/ListPersonTagRequest.py
aliyunsdkcdrs/request/v20201101/ListPersonTopRequest.py
aliyunsdkcdrs/request/v20201101/ListPersonTrackRequest.py
aliyunsdkcdrs/request/v20201101/ListRangeDeviceRequest.py
aliyunsdkcdrs/request/v20201101/ListStorageStatisticsRequest.py
aliyunsdkcdrs/request/v20201101/ListStructureStatisticsRequest.py
aliyunsdkcdrs/request/v20201101/ListTagMetricsRequest.py
aliyunsdkcdrs/request/v20201101/ListVehicleDetailsRequest.py
aliyun_python_sdk_cdrs-1.0.9.dist-info/LICENSE
aliyun_python_sdk_cdrs-1.0.9.dist-info/METADATA
aliyun_python_sdk_cdrs-1.0.9.dist-info/WHEEL
aliyun_python_sdk_cdrs-1.0.9.dist-info/top_level.txt
aliyun_python_sdk_cdrs-1.0.9.dist-info/RECORD
